plateau/__init__.py
plateau/__main__.py
plateau/codelists/__init__.py
plateau/codelists/codelists.json
plateau/models/__init__.py
plateau/models/attr_disaster_risk.py
plateau/models/base.py
plateau/models/bridge.py
plateau/models/building.py
plateau/models/cityfurniture.py
plateau/models/common.py
plateau/models/generics.py
plateau/models/landuse.py
plateau/models/relief.py
plateau/models/transportation.py
plateau/models/tunnel.py
plateau/models/urf_landslide.py
plateau/models/urf_zone/__init__.py
plateau/models/urf_zone/common.py
plateau/models/urf_zone/district_dev_plans.py
plateau/models/urf_zone/district_facilities.py
plateau/models/urf_zone/district_plans.py
plateau/models/urf_zone/districts_and_zones.py
plateau/models/urf_zone/promotion_areas.py
plateau/models/urf_zone/scheduled_areas.py
plateau/models/urf_zone/simple.py
plateau/models/urf_zone/urban_dev_projects.py
plateau/models/urf_zone/urban_facilities.py
plateau/models/uro_dm.py
plateau/models/uro_other_construction.py
plateau/models/uro_underground_building.py
plateau/models/uro_utility_network.py
plateau/models/vegetation.py
plateau/models/waterbody.py
plateau/namespaces.py
plateau/parse/__init__.py
plateau/parse/appearance.py
plateau/parse/geometry.py
plateau/parse/parser.py
plateau/types.py
plateau_py-0.0.1a5.dist-info/LICENSE.txt
plateau_py-0.0.1a5.dist-info/METADATA
plateau_py-0.0.1a5.dist-info/WHEEL
plateau_py-0.0.1a5.dist-info/RECORD
