Metadata-Version: 2.1
Name: plateau-py
Version: 0.0.1a5
Summary: Parsing the PLATEAU 3D City Models (CityGML) used in Japan.
Author: MIERUNE Inc.
Author-email: info@mierune.co.jp
Requires-Python: >=3.8,<4.0
Classifier: Programming Language :: Python :: 3
Classifier: Programming Language :: Python :: 3.8
Classifier: Programming Language :: Python :: 3.9
Classifier: Programming Language :: Python :: 3.10
Classifier: Programming Language :: Python :: 3.11
Requires-Dist: lxml (>=4.9.3,<5.0.0)
Requires-Dist: numpy (>=1.24)
